{
  "url": "https://vnexpress.net/dien-vien-hai-huu-tin-bi-de-nghi-truy-to-7-15-nam-tu-4530802.html",
  "title": "Dien vien hai Huu Tin bi de nghi truy to 7-15 nam tu",
  "published": "2022-11-01",
  "date_crawled": "2026-06-08T11:20:00+07:00",
  "content_markdown": "Bai bao VnExpress ve vu dien vien hai Tran Huu Tin cho biet co quan dieu tra da chuyen ho so de nghi truy to ve toi To chuc su dung trai phep chat ma tuy theo Dieu 255 Bo luat Hinh su. Noi dung vu an lien quan den viec Huu Tin va mot so nguoi bi phat hien tai can ho o quan 8, TP HCM sau khi su dung ma tuy. Bai viet cung neu mot dong pham bi xem xet them hanh vi tang tru trai phep chat ma tuy. Truong hop nay la du lieu tin tuc ve nghe si Viet Nam lien quan toi ma tuy, phu hop voi corpus RAG ve phap luat ma tuy va tin tuc nghe si. Metadata giu URL goc, ngay crawl, tieu de va ngay xuat ban de phuc vu citation."
}
